README.txt
setup.cfg
setup.py
docs/HISTORY.txt
docs/INSTALL.txt
docs/LICENSE.GPL
docs/LICENSE.txt
docs/API/api-objects.txt
docs/API/class-tree.html
docs/API/crarr.png
docs/API/epydoc.css
docs/API/epydoc.js
docs/API/frames.html
docs/API/help.html
docs/API/identifier-index.html
docs/API/index.html
docs/API/module-tree.html
docs/API/platecom.utils-module.html
docs/API/platecom.utils-pysrc.html
docs/API/platecom.utils.Extensions-module.html
docs/API/platecom.utils.Extensions-pysrc.html
docs/API/platecom.utils.Extensions.install-module.html
docs/API/platecom.utils.Extensions.install-pysrc.html
docs/API/platecom.utils.browser-module.html
docs/API/platecom.utils.browser-pysrc.html
docs/API/platecom.utils.browser.admin-module.html
docs/API/platecom.utils.browser.admin-pysrc.html
docs/API/platecom.utils.browser.admin.ContentTypes-class.html
docs/API/platecom.utils.browser.admin.Overview-class.html
docs/API/platecom.utils.browser.admin.ThesaurusUpload-class.html
docs/API/platecom.utils.browser.base-module.html
docs/API/platecom.utils.browser.base-pysrc.html
docs/API/platecom.utils.browser.base.BaseFormView-class.html
docs/API/platecom.utils.browser.base.BaseSettingsForm-class.html
docs/API/platecom.utils.browser.base.BaseView-class.html
docs/API/platecom.utils.browser.widgets-module.html
docs/API/platecom.utils.browser.widgets-pysrc.html
docs/API/platecom.utils.browser.widgets.MultiSelectionWidget-class.html
docs/API/platecom.utils.browser.widgets.OrderedMultiSelectionWidget-class.html
docs/API/platecom.utils.config-module.html
docs/API/platecom.utils.config-pysrc.html
docs/API/platecom.utils.content-module.html
docs/API/platecom.utils.content-pysrc.html
docs/API/platecom.utils.content.fields-module.html
docs/API/platecom.utils.content.fields-pysrc.html
docs/API/platecom.utils.content.fields.FieldEmptiness-class.html
docs/API/platecom.utils.content.fields.TextFieldEmptiness-class.html
docs/API/platecom.utils.content.multilingual-module.html
iccommunity.core.egg-info/PKG-INFO
iccommunity.core.egg-info/SOURCES.txt
iccommunity.core.egg-info/dependency_links.txt
iccommunity.core.egg-info/entry_points.txt
iccommunity.core.egg-info/namespace_packages.txt
iccommunity.core.egg-info/not-zip-safe
iccommunity.core.egg-info/requires.txt
iccommunity.core.egg-info/top_level.txt
